LICENSE.txt
README.md
setup.cfg
setup.py
native_sdk_core/__init__.py
native_sdk_core/api_client.py
native_sdk_core/configuration.py
native_sdk_core/rest.py
native_sdk_core.egg-info/PKG-INFO
native_sdk_core.egg-info/SOURCES.txt
native_sdk_core.egg-info/dependency_links.txt
native_sdk_core.egg-info/requires.txt
native_sdk_core.egg-info/top_level.txt
native_sdk_core/api/__init__.py
native_sdk_core/api/default_api.py
native_sdk_core/models/__init__.py
native_sdk_core/models/any_of_validation_error_loc_items.py
native_sdk_core/models/firm_quote.py
native_sdk_core/models/http_validation_error.py
native_sdk_core/models/indicative_quote.py
native_sdk_core/models/instrument.py
native_sdk_core/models/select_pool_pricing.py
native_sdk_core/models/validation_error.py
test/__init__.py
test/run_all.py
test/test_any_of_validation_error_loc_items.py
test/test_default_api.py
test/test_firm_quote.py
test/test_http_validation_error.py
test/test_indicative_quote.py
test/test_instrument.py
test/test_select_pool_pricing.py
test/test_validation_error.py
test/native_sdk_core/__init__.py
test/native_sdk_core/api_client.py
test/native_sdk_core/configuration.py
test/native_sdk_core/rest.py
test/native_sdk_core/api/__init__.py
test/native_sdk_core/api/default_api.py
test/native_sdk_core/models/__init__.py
test/native_sdk_core/models/any_of_validation_error_loc_items.py
test/native_sdk_core/models/firm_quote.py
test/native_sdk_core/models/http_validation_error.py
test/native_sdk_core/models/indicative_quote.py
test/native_sdk_core/models/instrument.py
test/native_sdk_core/models/select_pool_pricing.py
test/native_sdk_core/models/validation_error.py