Metadata-Version: 2.1
Name: native-sdk-core
Version: 0.1
Summary: nativeSDK
Home-page: 
Author-email: 
Keywords: Swagger,nativeSDK
License-File: LICENSE.txt
